alu.v
module alu(
    input [3:0] A,
    input [3:0] B,
    input [2:0] sel,
    output reg [3:0] Y
);

always @(*) begin
    case(sel)
        3'b000: Y = A + B;
        3'b001: Y = A - B;
        3'b010: Y = A & B;
        3'b011: Y = A | B;
        3'b100: Y = A ^ B;
        3'b101: Y = ~A;
        3'b110: Y = A << 1;
        3'b111: Y = A >> 1;
        default: Y = 4'b0000;
    endcase
end

endmodule

tb_alu.v

`timescale 1ns/1ps

module tb_alu;

reg [3:0] A;
reg [3:0] B;
reg [2:0] sel;
wire [3:0] Y;

alu uut(
    .A(A),
    .B(B),
    .sel(sel),
    .Y(Y)
);

initial begin
    $dumpfile("alu.vcd");
    $dumpvars(0,tb_alu);

    A = 4'b1010;
    B = 4'b0011;

    sel = 3'b000; #10;
    sel = 3'b001; #10;
    sel = 3'b010; #10;
    sel = 3'b011; #10;
    sel = 3'b100; #10;
    sel = 3'b101; #10;
    sel = 3'b110; #10;
    sel = 3'b111; #10;

    $finish;
end

endmodule

alu.vcd
$date
	Wed Jul 29 16:09:09 2026
$end
$version
	Icarus Verilog
$end
$timescale
	1ps
$end
$scope module tb_alu $end
$var wire 4 ! Y [3:0] $end
$var reg 4 " A [3:0] $end
$var reg 4 # B [3:0] $end
$var reg 3 $ sel [2:0] $end
$scope module uut $end
$var wire 4 % A [3:0] $end
$var wire 4 & B [3:0] $end
$var wire 3 ' sel [2:0] $end
$var reg 4 ( Y [3:0] $end
$upscope $end
$upscope $end
$enddefinitions $end
$comment Show the parameter values. $end
$dumpall
$end
#0
$dumpvars
b1101 (
b0 '
b11 &
b1010 %
b0 $
b11 #
b1010 "
b1101 !
$end
#10000
b111 !
b111 (
b1 $
b1 '
#20000
b10 !
b10 (
b10 $
b10 '
#30000
b1011 !
b1011 (
b11 $
b11 '
#40000
b1001 !
b1001 (
b100 $
b100 '
#50000
b101 !
b101 (
b101 $
b101 '
#60000
b100 !
b100 (
b110 $
b110 '
#70000
b101 !
b101 (
b111 $
b111 '
